{
  "configVersion": 1,
  "timestamp": 1685624057488,
  "index": "/index.html",
  "assetGroups": [
    {
      "name": "app",
      "installMode": "prefetch",
      "updateMode": "prefetch",
      "cacheQueryOptions": {
        "ignoreVary": true
      },
      "urls": [
        "/1033.915907daebd3d8ce.js",
        "/1118.ce3905daf84ba5d8.js",
        "/1217.28508cdc9ca25c68.js",
        "/1536.367e367dfabc3ca8.js",
        "/1566.22b3b2c31f1dca2c.js",
        "/1709.b60655e2b2edfaf9.js",
        "/197.94dd592d8c6bf824.js",
        "/2073.9f1e8acc2087da01.js",
        "/2349.09fb109797aa851d.js",
        "/2773.946b249f5968a7b1.js",
        "/2933.44cb7e703c6e9ad8.js",
        "/3326.5a9ee406f571e016.js",
        "/3583.310bc5bac55a791b.js",
        "/3648.b10cc0fc391aa31b.js",
        "/3804.cf3b71fed92586c3.js",
        "/388.de27ed1ef339abb9.js",
        "/4174.38e10c6dbd75a35e.js",
        "/4330.5887b27aaeb95c2e.js",
        "/4376.f0b199b4561fa64f.js",
        "/438.1a7bbd8bf0caa486.js",
        "/4432.04b96abf7e3a557f.js",
        "/4711.5cd12bfbb0519f37.js",
        "/4753.e23f135ded001030.js",
        "/4851.c8f502e126d1ebe9.js",
        "/4908.f9e7f9a85f9d5aea.js",
        "/4959.35f3dba2a91d62fd.js",
        "/5168.e361cc0e0a7de849.js",
        "/53.96d3169c66718af3.js",
        "/5349.7ebe87abc507e1eb.js",
        "/5652.78a504bead17fee2.js",
        "/5836.64699b3d7adadb46.js",
        "/6120.fd6eae035b6c540e.js",
        "/6560.faecbfdd6d97a2e0.js",
        "/657.45f13978a1f17acb.js",
        "/7544.6948a857efa6baf2.js",
        "/7602.8ca59d1d7efbdac0.js",
        "/7879.b601eed9b1f7e733.js",
        "/7895.5f590b5b4344817a.js",
        "/8034.ddb5cae648631583.js",
        "/8136.1d60f7beb213776f.js",
        "/8628.15423b595c2cfeab.js",
        "/8939.f65216c0be30644a.js",
        "/9016.3374f021c8d39791.js",
        "/9076.1a1937dcca7bbabe.js",
        "/9230.a33cba212750a42c.js",
        "/9324.911ab93c94a2718d.js",
        "/9325.3dcab6d9eb60d201.js",
        "/9434.03a48bde8152b137.js",
        "/9536.793beae7b0414c05.js",
        "/9654.876ad5faa2848a99.js",
        "/9824.f2859d9ac187053b.js",
        "/9922.aae37ec890e7af3f.js",
        "/9958.dd79a13fd1e62f24.js",
        "/common.415f808e0cb4d2c4.js",
        "/index.html",
        "/main.a9042d6936488110.js",
        "/manifest.webmanifest",
        "/polyfills-core-js.82337cdbd1fb98b6.js",
        "/polyfills-dom.5c5f23fb57b03028.js",
        "/polyfills.404967b56235ade2.js",
        "/runtime.e83d015ec75054b5.js",
        "/styles.262987a69e36664e.css"
      ],
      "patterns": []
    },
    {
      "name": "assets",
      "installMode": "lazy",
      "updateMode": "prefetch",
      "cacheQueryOptions": {
        "ignoreVary": true
      },
      "urls": [
        "/Futura.8baaa424d894fed8.ttf",
        "/assets/fonts/Futura.ttf",
        "/assets/icon/favicon.png",
        "/assets/icons/icon-128x128.png",
        "/assets/icons/icon-144x144.png",
        "/assets/icons/icon-152x152.png",
        "/assets/icons/icon-192x192.png",
        "/assets/icons/icon-512x512.png",
        "/assets/icons/icon-72x72.png",
        "/assets/icons/icon-96x96.png",
        "/assets/images/dark.avif",
        "/assets/images/icon.png",
        "/assets/images/light.avif",
        "/assets/images/sheshank_gupta.jpg",
        "/assets/images/sheshank_gupta_2.jpg",
        "/assets/logos/Ionic_Logo.svg",
        "/assets/logos/angular.svg",
        "/assets/logos/bootstrap.svg",
        "/assets/logos/css.svg",
        "/assets/logos/github.svg",
        "/assets/logos/html5.svg",
        "/assets/logos/javascript.svg",
        "/assets/logos/laravel-2.svg",
        "/assets/logos/tailwind.svg",
        "/assets/shapes.svg"
      ],
      "patterns": []
    }
  ],
  "dataGroups": [],
  "hashTable": {
    "/1033.915907daebd3d8ce.js": "ad4837888c1f0304624933f7f78967b268bd9e65",
    "/1118.ce3905daf84ba5d8.js": "a1752c96d910ab3fcef0eb3f8b114e190b06a014",
    "/1217.28508cdc9ca25c68.js": "9da29452543152563aedf74c19626204abca0ba8",
    "/1536.367e367dfabc3ca8.js": "a414727fc40b15c80f7bb5dcbbcc1d9215d4b97e",
    "/1566.22b3b2c31f1dca2c.js": "5c283f88eff1633d594c5b3ec7638ebffad63350",
    "/1709.b60655e2b2edfaf9.js": "58f0443fe4a8c0f6f9c6653b6a576c3eba13610a",
    "/197.94dd592d8c6bf824.js": "550d9c7526eddb3d337b48b824d3f5bb44e98910",
    "/2073.9f1e8acc2087da01.js": "f6aec51c6670c1683bbc92908ab2f7dee9feccbf",
    "/2349.09fb109797aa851d.js": "2d4dbbdb11dae30d3d8fc5e587282a6d03c8b0bc",
    "/2773.946b249f5968a7b1.js": "957472f651e6ccd17df896cd8e9f485881963061",
    "/2933.44cb7e703c6e9ad8.js": "b2331b6df0320d3bb959d89a042c049a7ff8f933",
    "/3326.5a9ee406f571e016.js": "599d0871654e5bd632e3da79dab9a5a9a81f7e62",
    "/3583.310bc5bac55a791b.js": "3e03d78f01ed34322fccebe11bbf12bb7cc50623",
    "/3648.b10cc0fc391aa31b.js": "3afb7f905d9386c149a3df20e2764d6d04929df7",
    "/3804.cf3b71fed92586c3.js": "1b99f9d2297fd1bab6ca2947c6eb7bebd31ef081",
    "/388.de27ed1ef339abb9.js": "7108f1834d12bb0c726d5da6a8770ae9bfc2c408",
    "/4174.38e10c6dbd75a35e.js": "14bf32bc19ce087658106060ca0953a7874f63cb",
    "/4330.5887b27aaeb95c2e.js": "7bbfb11573e7687ca1861020c8f8099a7f20b946",
    "/4376.f0b199b4561fa64f.js": "30aac0c2f91fbcbbce2829c505056333d3c76577",
    "/438.1a7bbd8bf0caa486.js": "b2ead57678d351dfd1b33308c06ebff288225c3c",
    "/4432.04b96abf7e3a557f.js": "324e05283a6c44ffe7c6ed87de6c99115e5e044d",
    "/4711.5cd12bfbb0519f37.js": "fd198a76b11bd092d42dd0596303a89c3cce83c4",
    "/4753.e23f135ded001030.js": "4d98f129df929724a0e8625edac795a6ef43b141",
    "/4851.c8f502e126d1ebe9.js": "6af65639cd7007cd0833c2961f0cb23f55f7c8a4",
    "/4908.f9e7f9a85f9d5aea.js": "e82a8e39be25ed155fcdde2d3de778fbc890fc12",
    "/4959.35f3dba2a91d62fd.js": "07bedeae41f6655c9494d399148348a038531c22",
    "/5168.e361cc0e0a7de849.js": "423835abbd2ba45ca6d458a652519e12ee802c0a",
    "/53.96d3169c66718af3.js": "b91d42292e2497f43562907a9302debcc6175eaa",
    "/5349.7ebe87abc507e1eb.js": "4de838df8bd8c0cfe5ea4ec006c62fd9f6637b2a",
    "/5652.78a504bead17fee2.js": "3f3c3a6e69358b2a8c1ea73f571d38c29d6d182c",
    "/5836.64699b3d7adadb46.js": "2290eef96293f318a79631e22624a953b543c6ff",
    "/6120.fd6eae035b6c540e.js": "8c92a85cd7108c1ef301446fd0f7ad7dacb130d9",
    "/6560.faecbfdd6d97a2e0.js": "adb966319479d6b6d18536d9585bbbd1f81d4b70",
    "/657.45f13978a1f17acb.js": "81bfb62127eea11ba2eb0db8aad01559477bab4e",
    "/7544.6948a857efa6baf2.js": "4f0fcea2a35c04d23941189fe5d26c4392baea8f",
    "/7602.8ca59d1d7efbdac0.js": "2e4fd912cb8e78e79ed2c160b2a0a1f8a37aaf9b",
    "/7879.b601eed9b1f7e733.js": "43745adc3e0ac91f8cbb946a953bee1bce44a557",
    "/7895.5f590b5b4344817a.js": "5423751bcce939d6bee8bb6d13dfd64783ef5dda",
    "/8034.ddb5cae648631583.js": "26b0434c4f0cc72a65ea99ed0ec598cb8e01456d",
    "/8136.1d60f7beb213776f.js": "672d045a51eea1ccef449914c0ac716d0a848cbb",
    "/8628.15423b595c2cfeab.js": "e33b17d83a8da568c6f2b44e9f82ab3569c8a427",
    "/8939.f65216c0be30644a.js": "ec3194caa09dfa36d9fc0b59043d7a573877509f",
    "/9016.3374f021c8d39791.js": "ac9fbcf8c6df0f00aa8d30bfb646264520663618",
    "/9076.1a1937dcca7bbabe.js": "e34976a1f6e7f215b32af34e654b56cd8f1ef26d",
    "/9230.a33cba212750a42c.js": "b3c4da4d115099b3ecae26d42c7bbcb8ca75b2a1",
    "/9324.911ab93c94a2718d.js": "418a02fc741bce0510263fefc46578300761a99d",
    "/9325.3dcab6d9eb60d201.js": "b4e416d5fda215edf45b249e36850f20c45d77b5",
    "/9434.03a48bde8152b137.js": "b5f10c70c5e91fbae5bc1ac7a2e80b0d5a837812",
    "/9536.793beae7b0414c05.js": "7b14653aa3ed6aab0d730ee6133ce20e5c225118",
    "/9654.876ad5faa2848a99.js": "c950f74dee7707bbb1f916c3663ce3baf0a12f29",
    "/9824.f2859d9ac187053b.js": "e71d3574b60acd8b1249a7eeb1fa968e1f845710",
    "/9922.aae37ec890e7af3f.js": "74498011f0726e852ad76816d306c89a42efb324",
    "/9958.dd79a13fd1e62f24.js": "6f5f1d8a6475c284855154d3aa5bb2981ac860b3",
    "/Futura.8baaa424d894fed8.ttf": "1bcd70a20cff464c22ac4c9519fb9f72dd9be22a",
    "/assets/fonts/Futura.ttf": "1bcd70a20cff464c22ac4c9519fb9f72dd9be22a",
    "/assets/icon/favicon.png": "7798b8e0eb61d7375c245af78bbf5c916932bf13",
    "/assets/icons/icon-128x128.png": "b993fb425c68171ffa6a6a72e4c7a89064ff5555",
    "/assets/icons/icon-144x144.png": "0fd05c1fcca1db0d85b436aec5fe3458b030e1fc",
    "/assets/icons/icon-152x152.png": "32c285a29ebb9bd80b018d429652640ab3821daa",
    "/assets/icons/icon-192x192.png": "2e3083c91cce5f26f0c06f0c375b907f1cdd381b",
    "/assets/icons/icon-512x512.png": "6da1c5d60166866806c09ce545402e71ff9c2599",
    "/assets/icons/icon-72x72.png": "5d4cb2a4916b68f0d9ff5cad215488d00fa224e5",
    "/assets/icons/icon-96x96.png": "ae716a71744f1c58f24873b0d1d07a02d2253c8c",
    "/assets/images/dark.avif": "131e719ff9c6e0dcc25defda53fafc95ddd79a46",
    "/assets/images/icon.png": "d4ffe3b89760342e417e188614ed263234b2492e",
    "/assets/images/light.avif": "e8b4064e2723803022a6f7909676248b86199105",
    "/assets/images/sheshank_gupta.jpg": "fe774bb724c6533da9263afb7fa5ee03fc1498c8",
    "/assets/images/sheshank_gupta_2.jpg": "8e006c37b19d46848f41f0c63d7045718d9ed231",
    "/assets/logos/Ionic_Logo.svg": "7f896b95a73702f280c70fa2e2bdaf735b7f873f",
    "/assets/logos/angular.svg": "5c3ad2788c41fd16ea65517d69e1fc62fe1254cc",
    "/assets/logos/bootstrap.svg": "6519775aa2723ab7cb89596a8e31d5053d53c56f",
    "/assets/logos/css.svg": "9565d7034eb5eb827d271ec19e398c899caccd58",
    "/assets/logos/github.svg": "dbc1eab99e6164d779de8c8973e1f85fa4dfb3d1",
    "/assets/logos/html5.svg": "0007b87d80cfd043519bfbd9f4191f2e356a7054",
    "/assets/logos/javascript.svg": "3546386ae62a16a8ecf830d33a6ce3f8e8df1530",
    "/assets/logos/laravel-2.svg": "a57e9a4c385894182c627a231c4a22f096720a56",
    "/assets/logos/tailwind.svg": "40eae5fc193aede15ac989f2e27cbda281684cdd",
    "/assets/shapes.svg": "5413e95adabcb2cb639970051f55e0ddb64ace53",
    "/common.415f808e0cb4d2c4.js": "69088c65a14abc22fd27a4c23a4e0c6eec3bdd76",
    "/index.html": "2b3c0431815fce0d371033ae348e22dc79a5e4b4",
    "/main.a9042d6936488110.js": "44678d529283891dbb7f33bcc8f9ddf87249b098",
    "/manifest.webmanifest": "0f128c8b69a416ea8f15cd783a8b03f9a9c54f65",
    "/polyfills-core-js.82337cdbd1fb98b6.js": "10d743722e24f852aa3634106c1047365238511f",
    "/polyfills-dom.5c5f23fb57b03028.js": "06f5dc30f55bf9a3d9c6f9bca07c0041a6bbdaa0",
    "/polyfills.404967b56235ade2.js": "c664f33320385f1ad492297d5cd9db021a0b32b5",
    "/runtime.e83d015ec75054b5.js": "f4cdac5dcdcaf7b3256c4c1b810abf951c1fd7c4",
    "/styles.262987a69e36664e.css": "67af4d39d58763c5633e9927f1def7fe9491bfe6"
  },
  "navigationUrls": [
    {
      "positive": true,
      "regex": "^\\/.*$"
    },
    {
      "positive": false,
      "regex": "^\\/(?:.+\\/)?[^/]*\\.[^/]*$"
    },
    {
      "positive": false,
      "regex": "^\\/(?:.+\\/)?[^/]*__[^/]*$"
    },
    {
      "positive": false,
      "regex": "^\\/(?:.+\\/)?[^/]*__[^/]*\\/.*$"
    }
  ],
  "navigationRequestStrategy": "performance"
}